gitmerge/__init__.py
gitmerge/cout.py
gitmerge/dirchecker.py
gitmerge/errors.py
gitmerge/gitmerge.py
gitmerge/merge.py
gitmerge-0.0.6.dist-info/AUTHORS.md
gitmerge-0.0.6.dist-info/LICENSE.txt
gitmerge-0.0.6.dist-info/METADATA
gitmerge-0.0.6.dist-info/WHEEL
gitmerge-0.0.6.dist-info/entry_points.txt
gitmerge-0.0.6.dist-info/top_level.txt
gitmerge-0.0.6.dist-info/RECORD
