Metadata-Version: 2.1
Name: gitmerge
Version: 0.0.6
Summary: Add your git commits from your corporate account to your private profile with gitmerge.
Home-page: UNKNOWN
Author: Benedikt Scheffler
Author-email: scheffler.benedikt@gmail.com
License: MIT
Platform: UNKNOWN
Classifier: Programming Language :: Python :: 3
Classifier: License :: OSI Approved :: MIT License
Requires-Python: >=3.8
License-File: LICENSE.txt
License-File: AUTHORS.md
Requires-Dist: GitPython (==3.1.24)
Requires-Dist: click
Requires-Dist: click-help-colors
Requires-Dist: regex
Provides-Extra: dev
Requires-Dist: coverage ; extra == 'dev'
